morphling/__init__.py
morphling/copy.py
morphling/input.py
morphling/output.py
morphling/word.py
morphling-0.2.0.dist-info/entry_points.txt
morphling-0.2.0.dist-info/LICENSE
morphling-0.2.0.dist-info/WHEEL
morphling-0.2.0.dist-info/METADATA
morphling-0.2.0.dist-info/RECORD
